setup.cfg
setup.py
InfluenceManager/__init__.py
InfluenceManager/definitions.py
InfluenceManager.egg-info/PKG-INFO
InfluenceManager.egg-info/SOURCES.txt
InfluenceManager.egg-info/dependency_links.txt
InfluenceManager.egg-info/requires.txt
InfluenceManager.egg-info/top_level.txt
InfluenceManager/bin/__init__.py
InfluenceManager/bin/log_daily_scores
InfluenceManager/bin/topic_query
InfluenceManager/scripts/__init__.py
InfluenceManager/scripts/topic_query.py
InfluenceManager/scripts/visualisation_manager.py