Metadata-Version: 1.0
Name: InfluenceManager
Version: 0.0.64
Summary: Backend module for retrieving top influencers from Twitter.
Home-page: UNKNOWN
Author: Ash Prince
Author-email: i7629228@bournemouth.ac.uk
License: UNKNOWN
Platform: UNKNOWN
